broker/__init__.py
broker/base.py
broker/client.py
broker/exceptions.py
broker/websockets.py
examples/OkexWsLasttrade.py
examples/__init__.py
examples/contract-examples.py
examples/contract_limit_free.py
examples/contract_ws_example.py
examples/csv_t.py
examples/examples.py
examples/okex_gateway(1).py
examples/option-examples.py
examples/t.py
examples/ws_examples.py
examples/ws_test.py
examples/zlibt.py
bhex-2.0.14.dist-info/LICENSE
bhex-2.0.14.dist-info/METADATA
bhex-2.0.14.dist-info/WHEEL
bhex-2.0.14.dist-info/top_level.txt
bhex-2.0.14.dist-info/RECORD
