Metadata-Version: 2.1
Name: bhex
Version: 2.0.14
Summary: Python SDK for Broker REST And Websocket API
Home-page: https://github.com/bhexopen/BHEX-OpenApi/tree/master/sdk/python
Author: BHex
Author-email: pip@bhex.com
License: UNKNOWN
Platform: UNKNOWN
Classifier: Programming Language :: Python :: 3
Classifier: License :: OSI Approved :: MIT License
Classifier: Operating System :: OS Independent
Requires-Dist: requests
Requires-Dist: six
Requires-Dist: twisted
Requires-Dist: autobahn
Requires-Dist: pyopenssl
Requires-Dist: service-identity
